jupyembed/__init__.py
jupyembed/cli.py
jupyembed/embed.py
jupyembed-0.1.0.dist-info/AUTHORS.rst
jupyembed-0.1.0.dist-info/LICENSE
jupyembed-0.1.0.dist-info/METADATA
jupyembed-0.1.0.dist-info/WHEEL
jupyembed-0.1.0.dist-info/entry_points.txt
jupyembed-0.1.0.dist-info/top_level.txt
jupyembed-0.1.0.dist-info/RECORD
