Metadata-Version: 2.1
Name: jupyembed
Version: 0.1.0
Summary: Embed your data in jupyter notebooks.
Home-page: https://github.com/MridulS/jupyembed
Author: Mridul Seth
Author-email: seth.mridul@gmail.com
License: BSD license
Keywords: jupyembed
Platform: UNKNOWN
Classifier: Development Status :: 2 - Pre-Alpha
Classifier: Intended Audience :: Developers
Classifier: License :: OSI Approved :: BSD License
Classifier: Natural Language :: English
Classifier: Programming Language :: Python :: 3
Classifier: Programming Language :: Python :: 3.7
Classifier: Programming Language :: Python :: 3.8
Requires-Python: >=3.7
Requires-Dist: Click (>=7.0)
